Workbook

Sheet Assumptions
A1: JCAMP SIGNAL SERVICE - FINANCIAL MODEL
A2: All blue values are inputs - change these to run scenarios
A4: PRICING ASSUMPTIONS
A5: Parameter | B5: Value | C5: Unit | D5: Notes
A6: Basic Tier Price | B6: 49 | C6: $/month | D6: Telegram signals only
A7: Pro Tier Price | B7: 99 | C7: $/month | D7: Discord + weekly analysis
A8: VIP Tier Price | B8: 199 | C8: $/month | D8: 1-on-1 calls + custom settings
A9: Basic Tier Mix | B9: 0.6 | C9: % | D9: 60% of subscribers
A10: Pro Tier Mix | B10: 0.3 | C10: % | D10: 30% of subscribers
A11: VIP Tier Mix | B11: 0.1 | C11: % | D11: 10% of subscribers
A12: Weighted ARPU | B12: =B6*B9+B7*B10+B8*B11 -> 79 | C12: $/month | D12: Formula: tier mix weighted average
A14: COST ASSUMPTIONS
A15: Parameter | B15: Value | C15: Unit | D15: Notes
A16: VPS Primary | B16: 40 | C16: $/month | D16: DigitalOcean/Linode 4 core 8GB
A17: VPS Backup | B17: 40 | C17: $/month | D17: Redundancy for 99.9% uptime
A18: Claude Pro | B18: 20 | C18: $/month | D18: Development tool - $17/mo annual
A19: Domain + SSL | B19: 1 | C19: $/month | D19: Namecheap + LetsEncrypt
A20: Stripe Fee Rate | B20: 0.029 | C20: % | D20: 2.9% per transaction
A21: Stripe Fee Fixed | B21: 0.3 | C21: $/txn | D21: Plus $0.30 per transaction
A22: MT5 Account Capital | B22: 500 | C22: $ one-time | D22: Initial trading capital
A24: GROWTH ASSUMPTIONS
A25: Parameter | B25: Value | C25: Unit | D25: Notes
A26: Monthly Churn Rate | B26: 0.1 | C26: % | D26: Industry avg 8-12% for signals
A27: Month 1 New Subs | B27: 10 | C27: subscribers | D27: Friends + early followers
A28: Monthly Growth Rate | B28: 0.15 | C28: % | D28: Organic + content marketing
A29: Free Trial Conversion | B29: 0.2 | C29: % | D29: Trial to paid conversion
A30: Annual Discount | B30: 0.3 | C30: % | D30: 30% off for annual plans
A33: CLAUDE AI SUBSCRIPTION REFERENCE
A34: Plan | B34: Price | C34: Usage | D34: Best For
A35: Free | B35: $0/month | C35: Limited, resets 5 hours | D35: Testing
A36: Pro | B36: $20/month ($17 annual) | C36: 5x Free usage | D36: Development
A37: Max 5x | B37: $100/month | C37: 25x Free usage | D37: Heavy coding
A38: Max 20x | B38: $200/month | C38: 100x Free usage | D38: Full-time coding
A39: Team | B39: $25-30/user/month | C39: Pro + admin (5+ users) | D39: Small teams

Sheet Monthly Projections
A1: 24-MONTH SUBSCRIBER & REVENUE PROJECTIONS
A3: Month | B3: New Subs | C3: Churned | D3: Total Subs | E3: Basic | F3: Pro | G3: VIP | H3: Gross Rev | I3: Stripe Fees | J3: Fixed Costs | K3: Net Revenue | L3: Cum. Revenue | M3: Cum. Profit
A4: 1 | B4: =Assumptions!B27 -> 10 | C4: 0 | D4: =B4-C4 -> 10 | E4: =ROUND(D4*Assumptions!B9,0) -> 6 | F4: =ROUND(D4*Assumptions!B10,0) -> 3 | G4: =D4-E4-F4 -> 1 | H4: =E4*Assumptions!B6+F4*Assumptions!B7+G4*Assumptions!B8 -> 790 | I4: =H4*Assumptions!B20+D4*Assumptions!B21 -> 25.91 | J4: =Assumptions!B16+Assumptions!B17+Assumptions!B18+Assumptions!B19 -> 101 | K4: =H4-I4-J4 -> 663.09 | L4: =H4 -> 790 | M4: =K4 -> 663.09
A5: 2 | B5: =ROUND(D4*Assumptions!$B$28,0) -> 2 | C5: =ROUND(D4*Assumptions!$B$26,0) -> 1 | D5: =D4+B5-C5 -> 11 | E5: =ROUND(D5*Assumptions!$B$9,0) -> 7 | F5: =ROUND(D5*Assumptions!$B$10,0) -> 3 | G5: =D5-E5-F5 -> 1 | H5: =E5*Assumptions!$B$6+F5*Assumptions!$B$7+G5*Assumptions!$B$8 -> 839 | I5: =H5*Assumptions!$B$20+D5*Assumptions!$B$21 -> 27.631 | J5: =Assumptions!$B$16+Assumptions!$B$17+Assumptions!$B$18+Assumptions!$B$19 -> 101 | K5: =H5-I5-J5 -> 710.369 | L5: =L4+H5 -> 1629 | M5: =M4+K5 -> 1373.459
A6: 3 | B6: =ROUND(D5*Assumptions!$B$28,0) -> 2 | C6: =ROUND(D5*Assumptions!$B$26,0) -> 1 | D6: =D5+B6-C6 -> 12 | E6: =ROUND(D6*Assumptions!$B$9,0) -> 7 | F6: =ROUND(D6*Assumptions!$B$10,0) -> 4 | G6: =D6-E6-F6 -> 1 | H6: =E6*Assumptions!$B$6+F6*Assumptions!$B$7+G6*Assumptions!$B$8 -> 938 | I6: =H6*Assumptions!$B$20+D6*Assumptions!$B$21 -> 30.802 | J6: =Assumptions!$B$16+Assumptions!$B$17+Assumptions!$B$18+Assumptions!$B$19 -> 101 | K6: =H6-I6-J6 -> 806.198 | L6: =L5+H6 -> 2567 | M6: =M5+K6 -> 2179.657
A7: 4 | B7: =ROUND(D6*Assumptions!$B$28,0) -> 2 | C7: =ROUND(D6*Assumptions!$B$26,0) -> 1 | D7: =D6+B7-C7 -> 13 | E7: =ROUND(D7*Assumptions!$B$9,0) -> 8 | F7: =ROUND(D7*Assumptions!$B$10,0) -> 4 | G7: =D7-E7-F7 -> 1 | H7: =E7*Assumptions!$B$6+F7*Assumptions!$B$7+G7*Assumptions!$B$8 -> 987 | I7: =H7*Assumptions!$B$20+D7*Assumptions!$B$21 -> 32.523 | J7: =Assumptions!$B$16+Assumptions!$B$17+Assumptions!$B$18+Assumptions!$B$19 -> 101 | K7: =H7-I7-J7 -> 853.477 | L7: =L6+H7 -> 3554 | M7: =M6+K7 -> 3033.134
A8: 5 | B8: =ROUND(D7*Assumptions!$B$28,0) -> 2 | C8: =ROUND(D7*Assumptions!$B$26,0) -> 1 | D8: =D7+B8-C8 -> 14 | E8: =ROUND(D8*Assumptions!$B$9,0) -> 8 | F8: =ROUND(D8*Assumptions!$B$10,0) -> 4 | G8: =D8-E8-F8 -> 2 | H8: =E8*Assumptions!$B$6+F8*Assumptions!$B$7+G8*Assumptions!$B$8 -> 1186 | I8: =H8*Assumptions!$B$20+D8*Assumptions!$B$21 -> 38.594 | J8: =Assumptions!$B$16+Assumptions!$B$17+Assumptions!$B$18+Assumptions!$B$19 -> 101 | K8: =H8-I8-J8 -> 1046.406 | L8: =L7+H8 -> 4740 | M8: =M7+K8 -> 4079.54
A9: 6 | B9: =ROUND(D8*Assumptions!$B$28,0) -> 2 | C9: =ROUND(D8*Assumptions!$B$26,0) -> 1 | D9: =D8+B9-C9 -> 15 | E9: =ROUND(D9*Assumptions!$B$9,0) -> 9 | F9: =ROUND(D9*Assumptions!$B$10,0) -> 5 | G9: =D9-E9-F9 -> 1 | H9: =E9*Assumptions!$B$6+F9*Assumptions!$B$7+G9*Assumptions!$B$8 -> 1135 | I9: =H9*Assumptions!$B$20+D9*Assumptions!$B$21 -> 37.415 | J9: =Assumptions!$B$16+Assumptions!$B$17+Assumptions!$B$18+Assumptions!$B$19 -> 101 | K9: =H9-I9-J9 -> 996.585 | L9: =L8+H9 -> 5875 | M9: =M8+K9 -> 5076.125
A10: 7 | B10: =ROUND(D9*Assumptions!$B$28,0) -> 2 | C10: =ROUND(D9*Assumptions!$B$26,0) -> 2 | D10: =D9+B10-C10 -> 15 | E10: =ROUND(D10*Assumptions!$B$9,0) -> 9 | F10: =ROUND(D10*Assumptions!$B$10,0) -> 5 | G10: =D10-E10-F10 -> 1 | H10: =E10*Assumptions!$B$6+F10*Assumptions!$B$7+G10*Assumptions!$B$8 -> 1135 | I10: =H10*Assumptions!$B$20+D10*Assumptions!$B$21 -> 37.415 | J10: =Assumptions!$B$16+Assumptions!$B$17+Assumptions!$B$18+Assumptions!$B$19 -> 101 | K10: =H10-I10-J10 -> 996.585 | L10: =L9+H10 -> 7010 | M10: =M9+K10 -> 6072.71
A11: 8 | B11: =ROUND(D10*Assumptions!$B$28,0) -> 2 | C11: =ROUND(D10*Assumptions!$B$26,0) -> 2 | D11: =D10+B11-C11 -> 15 | E11: =ROUND(D11*Assumptions!$B$9,0) -> 9 | F11: =ROUND(D11*Assumptions!$B$10,0) -> 5 | G11: =D11-E11-F11 -> 1 | H11: =E11*Assumptions!$B$6+F11*Assumptions!$B$7+G11*Assumptions!$B$8 -> 1135 | I11: =H11*Assumptions!$B$20+D11*Assumptions!$B$21 -> 37.415 | J11: =Assumptions!$B$16+Assumptions!$B$17+Assumptions!$B$18+Assumptions!$B$19 -> 101 | K11: =H11-I11-J11 -> 996.585 | L11: =L10+H11 -> 8145 | M11: =M10+K11 -> 7069.295
A12: 9 | B12: =ROUND(D11*Assumptions!$B$28,0) -> 2 | C12: =ROUND(D11*Assumptions!$B$26,0) -> 2 | D12: =D11+B12-C12 -> 15 | E12: =ROUND(D12*Assumptions!$B$9,0) -> 9 | F12: =ROUND(D12*Assumptions!$B$10,0) -> 5 | G12: =D12-E12-F12 -> 1 | H12: =E12*Assumptions!$B$6+F12*Assumptions!$B$7+G12*Assumptions!$B$8 -> 1135 | I12: =H12*Assumptions!$B$20+D12*Assumptions!$B$21 -> 37.415 | J12: =Assumptions!$B$16+Assumptions!$B$17+Assumptions!$B$18+Assumptions!$B$19 -> 101 | K12: =H12-I12-J12 -> 996.585 | L12: =L11+H12 -> 9280 | M12: =M11+K12 -> 8065.88
A13: 10 | B13: =ROUND(D12*Assumptions!$B$28,0) -> 2 | C13: =ROUND(D12*Assumptions!$B$26,0) -> 2 | D13: =D12+B13-C13 -> 15 | E13: =ROUND(D13*Assumptions!$B$9,0) -> 9 | F13: =ROUND(D13*Assumptions!$B$10,0) -> 5 | G13: =D13-E13-F13 -> 1 | H13: =E13*Assumptions!$B$6+F13*Assumptions!$B$7+G13*Assumptions!$B$8 -> 1135 | I13: =H13*Assumptions!$B$20+D13*Assumptions!$B$21 -> 37.415 | J13: =Assumptions!$B$16+Assumptions!$B$17+Assumptions!$B$18+Assumptions!$B$19 -> 101 | K13: =H13-I13-J13 -> 996.585 | L13: =L12+H13 -> 10415 | M13: =M12+K13 -> 9062.465
A14: 11 | B14: =ROUND(D13*Assumptions!$B$28,0) -> 2 | C14: =ROUND(D13*Assumptions!$B$26,0) -> 2 | D14: =D13+B14-C14 -> 15 | E14: =ROUND(D14*Assumptions!$B$9,0) -> 9 | F14: =ROUND(D14*Assumptions!$B$10,0) -> 5 | G14: =D14-E14-F14 -> 1 | H14: =E14*Assumptions!$B$6+F14*Assumptions!$B$7+G14*Assumptions!$B$8 -> 1135 | I14: =H14*Assumptions!$B$20+D14*Assumptions!$B$21 -> 37.415 | J14: =Assumptions!$B$16+Assumptions!$B$17+Assumptions!$B$18+Assumptions!$B$19 -> 101 | K14: =H14-I14-J14 -> 996.585 | L14: =L13+H14 -> 11550 | M14: =M13+K14 -> 10059.05
A15: 12 | B15: =ROUND(D14*Assumptions!$B$28,0) -> 2 | C15: =ROUND(D14*Assumptions!$B$26,0) -> 2 | D15: =D14+B15-C15 -> 15 | E15: =ROUND(D15*Assumptions!$B$9,0) -> 9 | F15: =ROUND(D15*Assumptions!$B$10,0) -> 5 | G15: =D15-E15-F15 -> 1 | H15: =E15*Assumptions!$B$6+F15*Assumptions!$B$7+G15*Assumptions!$B$8 -> 1135 | I15: =H15*Assumptions!$B$20+D15*Assumptions!$B$21 -> 37.415 | J15: =Assumptions!$B$16+Assumptions!$B$17+Assumptions!$B$18+Assumptions!$B$19 -> 101 | K15: =H15-I15-J15 -> 996.585 | L15: =L14+H15 -> 12685 | M15: =M14+K15 -> 11055.635
A16: 13 | B16: =ROUND(D15*Assumptions!$B$28,0) -> 2 | C16: =ROUND(D15*Assumptions!$B$26,0) -> 2 | D16: =D15+B16-C16 -> 15 | E16: =ROUND(D16*Assumptions!$B$9,0) -> 9 | F16: =ROUND(D16*Assumptions!$B$10,0) -> 5 | G16: =D16-E16-F16 -> 1 | H16: =E16*Assumptions!$B$6+F16*Assumptions!$B$7+G16*Assumptions!$B$8 -> 1135 | I16: =H16*Assumptions!$B$20+D16*Assumptions!$B$21 -> 37.415 | J16: =Assumptions!$B$16+Assumptions!$B$17+Assumptions!$B$18+Assumptions!$B$19 -> 101 | K16: =H16-I16-J16 -> 996.585 | L16: =L15+H16 -> 13820 | M16: =M15+K16 -> 12052.22
... A27: 24 | B27: =ROUND(D26*Assumptions!$B$28,0) -> 2 | C27: =ROUND(D26*Assumptions!$B$26,0) -> 2 | D27: =D26+B27-C27 -> 15 | E27: =ROUND(D27*Assumptions!$B$9,0) -> 9 | F27: =ROUND(D27*Assumptions!$B$10,0) -> 5 | G27: =D27-E27-F27 -> 1 | H27: =E27*Assumptions!$B$6+F27*Assumptions!$B$7+G27*Assumptions!$B$8 -> 1135 | I27: =H27*Assumptions!$B$20+D27*Assumptions!$B$21 -> 37.415 | J27: =Assumptions!$B$16+Assumptions!$B$17+Assumptions!$B$18+Assumptions!$B$19 -> 101 | K27: =H27-I27-J27 -> 996.585 | L27: =L26+H27 -> 26305 | M27: =M26+K27 -> 23014.655

Sheet Scenarios
A1: SCENARIO ANALYSIS - 24 MONTH OUTCOMES
A3: Scenario | B3: Subscribers | C3: Monthly Revenue | D3: Monthly Costs | E3: Monthly Profit | F3: Annual Profit
A4: Break-even | B4: 4 | C4: =B4*Assumptions!B12 -> 316 | D4: =Assumptions!B16+Assumptions!B17+Assumptions!B18+Assumptions!B19 -> 101 | E4: =C4-D4 -> 215 | F4: =E4*12 -> 2580
A5: Pessimistic | B5: 50 | C5: =B5*Assumptions!B12 -> 3950 | D5: =Assumptions!B16+Assumptions!B17+Assumptions!B18+Assumptions!B19+C5*0.035 -> 239.25 | E5: =C5-D5 -> 3710.75 | F5: =E5*12 -> 44529
A6: Realistic | B6: 75 | C6: =B6*Assumptions!B12 -> 5925 | D6: =Assumptions!B16+Assumptions!B17+Assumptions!B18+Assumptions!B19+C6*0.035 -> 308.375 | E6: =C6-D6 -> 5616.625 | F6: =E6*12 -> 67399.5
A7: Optimistic | B7: 100 | C7: =B7*Assumptions!B12 -> 7900 | D7: =Assumptions!B16+Assumptions!B17+Assumptions!B18+Assumptions!B19+C7*0.035 -> 377.5 | E7: =C7-D7 -> 7522.5 | F7: =E7*12 -> 90270
A8: Stretch | B8: 150 | C8: =B8*Assumptions!B12 -> 11850 | D8: =Assumptions!B16+Assumptions!B17+Assumptions!B18+Assumptions!B19+C8*0.035 -> 515.75 | E8: =C8-D8 -> 11334.25 | F8: =E8*12 -> 136011
A11: DIVERSIFIED REVENUE STREAMS (ADDITIONAL)
A12: Revenue Stream | B12: Monthly Potential | C12: Probability | D12: Expected Value | E12: Notes
A13: Broker Affiliates | B13: 3500 | C13: 0.6 | D13: =B13*C13 -> 2100 | E13: 10 refs @ $350 avg
A14: Backtesting Course | B14: 1500 | C14: 0.4 | D14: =B14*C14 -> 600 | E14: 5 sales @ $300
A15: Custom EA Sales | B15: 3000 | C15: 0.3 | D15: =B15*C15 -> 900 | E15: 2 sales @ $1500
A16: YouTube Revenue | B16: 75 | C16: 0.8 | D16: =B16*C16 -> 60 | E16: After 1000 subs
A17: TOTAL ADDITIONAL | B17: =SUM(B13:B16) -> 8075 | D17: =SUM(D13:D16) -> 3660

Sheet Costs
A1: DETAILED COST BREAKDOWN BY PHASE
A3: Cost Item | B3: Development Phase | C3: Live Phase | D3: Notes
A4: VPS Primary (4 core, 8GB) | B4: 40 | C4: 40 | D4: DigitalOcean/Linode
A5: VPS Backup (redundancy) | B5: 0 | C5: 40 | D5: Required for 99.9% uptime
A6: Claude Pro Subscription | B6: 20 | C6: 20 | D6: $17/mo with annual billing
A7: Domain Registration | B7: 1 | C7: 1 | D7: Namecheap annual
A8: SSL Certificate | B8: 0 | C8: 0 | D8: Free via LetsEncrypt
A9: Telegram Bot API | B9: 0 | C9: 0 | D9: Free
A10: Discord Bot Hosting | B10: 0 | C10: 0 | D10: Included in VPS
A11: Stripe Payment Fees | B11: 0 | C11: Variable | D11: 2.9% + $0.30/txn
A12: SendGrid Email | B12: 0 | C12: 0 | D12: Free tier 100/day
A13: Myfxbook | B13: 0 | C13: 0 | D13: Free API
A14: MT5 Demo Account | B14: 0 | C14: 0 | D14: Free
A15: MT5 Real Account | B15: 500 | C15: 0 | D15: One-time capital
A16: Monitoring (UptimeRobot) | B16: 0 | C16: 0 | D16: Free tier
A18: TOTAL FIXED MONTHLY | B18: =SUM(B4:B14) -> 61 | C18: =B16+B17+B18+B19 -> 561 | D18: Excludes variable Stripe
A19: TOTAL ONE-TIME | B19: 500 | C19: 0 | D19: MT5 capital

Sheet Timeline
A1: PROJECT TIMELINE - 24 MONTHS TO $5K/MONTH
A3: Phase | B3: Description | C3: Duration | D3: Effort | E3: Key Deliverable | F3: Cumulative Time
A4: 1 | B4: Complete Phase 5.2 | C4: 2 weeks | D4: 6-8 hrs | E4: C# viewer 100% | F4: 2 weeks
A5: 2 | B5: Multi-Pair Validation | C5: 2 weeks | D5: 10-12 hrs | E5: 6-pair backtest | F5: 4 weeks
A6: 3 | B6: Live Trading + Myfxbook | C6: 4 weeks | D6: 26-34 hrs | E6: Demo trading live | F6: 8 weeks
A7: 4 | B7: Extended Validation | C7: 44-52 weeks | D7: 15-20 hrs | E7: 12-month track record | F7: 52-60 weeks
A8: 5 | B8: Signal Service MVP | C8: 4 weeks | D8: 18-24 hrs | E8: Telegram + landing | F8: 56-64 weeks
A9: 6 | B9: Beta Launch | C9: 6 weeks | D9: 10-15 hrs | E9: 15-20 beta users | F9: 62-70 weeks
A10: 7 | B10: Public Launch | C10: 4 weeks | D10: 15-20 hrs | E10: First 30 subscribers | F10: 66-74 weeks
A11: 8 | B11: Scale to $5k/month | C11: 24-32 weeks | D11: 15-20 hrs/mo | E11: 100+ subscribers | F11: 90-106 weeks
